<?xml version = '1.0' encoding = 'UTF-8'?>
<Table class="oracle.dbtools.crest.model.design.relational.Table" id="9EA8CAF9-A49C-F81C-4CE9-9CDCF464BCB7" directorySegmentName="seg_0" name="TIPO_LOGRADOURO">
<createdBy>root</createdBy>
<createdTime>2013-03-10 11:43:53 UTC</createdTime>
<generatorID>CCB9A1E6-13D9-2434-0EF3-2DAD5F705979</generatorID>
<ownerDesignName>am_banco</ownerDesignName>
<pkName>TIPO_LOGRADOURO PK</pkName>
<fonts>
<FontObject class="oracle.dbtools.crest.model.design.FontObjectWr">
<foType>Title</foType>
<fontStyle>1</fontStyle>
<colorRGB>-16776961</colorRGB>
</FontObject>
<FontObject class="oracle.dbtools.crest.model.design.FontObjectWr">
<foType>Column</foType>
<colorRGB>-16777216</colorRGB>
</FontObject>
<FontObject class="oracle.dbtools.crest.model.design.FontObjectWr">
<foType>Datatype</foType>
<colorRGB>-16744448</colorRGB>
</FontObject>
<FontObject class="oracle.dbtools.crest.model.design.FontObjectWr">
<foType>PK Element</foType>
<colorRGB>-16776961</colorRGB>
</FontObject>
<FontObject class="oracle.dbtools.crest.model.design.FontObjectWr">
<foType>FK Element</foType>
<colorRGB>-16777216</colorRGB>
</FontObject>
<FontObject class="oracle.dbtools.crest.model.design.FontObjectWr">
<foType>UK Element</foType>
<colorRGB>-16776961</colorRGB>
</FontObject>
<FontObject class="oracle.dbtools.crest.model.design.FontObjectWr">
<foType>Not Null</foType>
<colorRGB>-65536</colorRGB>
</FontObject>
<FontObject class="oracle.dbtools.crest.model.design.FontObjectWr">
<foType>Key</foType>
<colorRGB>-16777216</colorRGB>
</FontObject>
</fonts>
<columns>
<Column class="oracle.dbtools.crest.model.design.relational.Column" name="ID_TIPO_LOGRADOURO" id="9B784A76-9A92-DCB8-83E2-7689D32D8FA4">
<createdBy>root</createdBy>
<createdTime>2013-03-10 11:43:53 UTC</createdTime>
<generatorID>DB24FE63-17B7-29DF-EDBF-14031D9CD397</generatorID>
<ownerDesignName>am_banco</ownerDesignName>
<useDomainConstraints>false</useDomainConstraints>
<use>1</use>
<logicalDatatype>LOGDT019</logicalDatatype>
<dataTypePrecision>10</dataTypePrecision>
<dataTypeScale>0</dataTypeScale>
<previousColumn>false</previousColumn>
<autoIncrementCycle>false</autoIncrementCycle>
</Column>
<Column class="oracle.dbtools.crest.model.design.relational.Column" name="NOME" id="8EF579CF-B8CC-6557-43F2-33729736F779">
<createdBy>root</createdBy>
<createdTime>2013-03-10 11:43:53 UTC</createdTime>
<generatorID>4322C218-5090-56A2-7572-BD7115276F30</generatorID>
<ownerDesignName>am_banco</ownerDesignName>
<useDomainConstraints>false</useDomainConstraints>
<use>1</use>
<logicalDatatype>LOGDT024</logicalDatatype>
<dataTypeSize>256</dataTypeSize>
<previousColumn>false</previousColumn>
<autoIncrementCycle>false</autoIncrementCycle>
</Column>
</columns>
<indexes>
<ind_PK_UK class="oracle.dbtools.crest.model.design.relational.Index" id="6AEB2B74-67BD-B1D8-F85B-148E877188A1" name="TIPO_LOGRADOURO PK">
<createdBy>root</createdBy>
<createdTime>2013-03-10 11:43:53 UTC</createdTime>
<generatorID>3F038A52-C2D5-8C4E-D197-2E965523BDF8</generatorID>
<ownerDesignName>am_banco</ownerDesignName>
<pk>true</pk>
<indexState>Primary Constraint</indexState>
<indexColumnUsage>
<colUsage columnID="9B784A76-9A92-DCB8-83E2-7689D32D8FA4"/>
</indexColumnUsage>
</ind_PK_UK>
</indexes>
</Table>